pycocotools/__init__.py
pycocotools/coco.py
pycocotools/cocoeval.py
pycocotools/mask.py
pycocotools/maskutils.py
fe_pycocotools-1.0.dist-info/METADATA
fe_pycocotools-1.0.dist-info/WHEEL
fe_pycocotools-1.0.dist-info/top_level.txt
fe_pycocotools-1.0.dist-info/RECORD
