Metadata-Version: 2.1
Name: fe-pycocotools
Version: 1.0
Summary: UNKNOWN
Home-page: UNKNOWN
Author: UNKNOWN
Author-email: UNKNOWN
License: UNKNOWN
Platform: UNKNOWN
Requires-Dist: setuptools (>=18.0)
Requires-Dist: matplotlib (>=2.1.0)
